src/__init__.py
src/__main__.py
src/main.py
src/server.py
jc_udp_game-0.0.1.dist-info/METADATA
jc_udp_game-0.0.1.dist-info/WHEEL
jc_udp_game-0.0.1.dist-info/entry_points.txt
jc_udp_game-0.0.1.dist-info/top_level.txt
jc_udp_game-0.0.1.dist-info/RECORD
